LICENSE.md
data_point_client/__init__.py
data_point_client/api/__init__.py
data_point_client/api/data_export/__init__.py
data_point_client/api/data_export/data_export_create_csv_export.py
data_point_client/api/data_point/__init__.py
data_point_client/api/data_point/data_point_append_execution_result_data.py
data_point_client/api/data_point/data_point_append_time_series_data.py
data_point_client/api/data_point/data_point_create_chiller_samples.py
data_point_client/api/data_point/data_point_create_data_point.py
data_point_client/api/data_point/data_point_delete_data_point.py
data_point_client/api/data_point/data_point_delete_data_point_cleanup_rule.py
data_point_client/api/data_point/data_point_get_data.py
data_point_client/api/data_point/data_point_get_data_point.py
data_point_client/api/data_point/data_point_get_data_point_by_version.py
data_point_client/api/data_point/data_point_get_data_points.py
data_point_client/api/data_point/data_point_get_tags.py
data_point_client/api/data_point/data_point_get_tags_2.py
data_point_client/api/data_point/data_point_update_constant_data.py
data_point_client/api/data_point/data_point_update_data_point.py
data_point_client/api/data_point/data_point_update_data_point_cleanup_rule.py
data_point_client/api/data_point/data_point_update_data_point_unit.py
data_point_client/api/data_point/data_point_update_time_series_data.py
data_point_client/api/files/__init__.py
data_point_client/api/files/files_get.py
data_point_client/api/files/files_get_list.py
data_point_client/api/files/files_get_raw.py
data_point_client/client.py
data_point_client/models/__init__.py
data_point_client/models/append_execution_result_data_request.py
data_point_client/models/append_time_series_request.py
data_point_client/models/calculation_origin.py
data_point_client/models/constant_data_bucket.py
data_point_client/models/constant_data_point_data.py
data_point_client/models/data_bucket_base.py
data_point_client/models/data_export_request.py
gnista_library-2.0.2.dist-info/LICENSE.md
gnista_library-2.0.2.dist-info/WHEEL
gnista_library-2.0.2.dist-info/METADATA
gnista_library-2.0.2.dist-info/RECORD
