Metadata-Version: 2.1
Name: gnista-library
Version: 2.0.2
Summary: A client library for accessing gnista.io
Home-page: https://gnista.io
License: MIT
Author: Markus Hoffmann
Author-email: markus@campfire-solutions.com
Requires-Python: >=3.8,<3.11
Classifier: License :: OSI Approved :: MIT License
Classifier: Programming Language :: Python :: 3
Classifier: Programming Language :: Python :: 3.8
Classifier: Programming Language :: Python :: 3.9
Classifier: Programming Language :: Python :: 3.10
Requires-Dist: PyJWT (>=2.3.0,<3.0.0)
Requires-Dist: attrs (>=20.1.0,<23.0.0)
Requires-Dist: colorama (>=0.4.4,<0.5.0)
Requires-Dist: httpx (>=0.15.4,<1.0.0)
Requires-Dist: keyring (>=23.5.0,<24.0.0)
Requires-Dist: oauth2-client (>=1.2.1,<2.0.0)
Requires-Dist: pandas (>=1.3.2,<2.0.0)
Requires-Dist: python-dateutil (>=2.8.0,<3.0.0)
Requires-Dist: structlog (>=21.0.0,<22.0.0)
Project-URL: Repository, https://gitlab.com/campfiresolutions/public/gnista.io-python-library.git
